elliptical_distribution_toolkit/__init__.py
elliptical_distribution_toolkit/toolkit.py
elliptical_distribution_toolkit-0.2.0.dist-info/licenses/LICENSE
elliptical_distribution_toolkit-0.2.0.dist-info/METADATA
elliptical_distribution_toolkit-0.2.0.dist-info/WHEEL
elliptical_distribution_toolkit-0.2.0.dist-info/top_level.txt
elliptical_distribution_toolkit-0.2.0.dist-info/RECORD
