Metadata-Version: 2.4
Name: elliptical-distribution-toolkit
Version: 0.2.0
Summary: Tools related to multivariate elliptical distributions
Home-page: https://gitlab.com/elliptical-distribution-toolkit-dev/elliptical-distribution-toolkit
Author: Jay Damask
Author-email: jaydamask@buell-lane-press.co
License:                                  Apache License
Requires-Python: >=3.7
License-File: LICENSE
Requires-Dist: numpy
Requires-Dist: scipy
Provides-Extra: dev
Requires-Dist: setuptools; extra == "dev"
Requires-Dist: bump-my-version; extra == "dev"
Provides-Extra: testing
Requires-Dist: unittest2; extra == "testing"
Dynamic: author
Dynamic: home-page
Dynamic: license-file
Dynamic: requires-python
